torch_tb_profiler/__init__.py
torch_tb_profiler/consts.py
torch_tb_profiler/multiprocessing.py
torch_tb_profiler/plugin.py
torch_tb_profiler/run.py
torch_tb_profiler/utils.py
torch_tb_profiler/config/config.ini
torch_tb_profiler/io/__init__.py
torch_tb_profiler/io/azureblob.py
torch_tb_profiler/io/base.py
torch_tb_profiler/io/cache.py
torch_tb_profiler/io/file.py
torch_tb_profiler/io/gs.py
torch_tb_profiler/io/utils.py
torch_tb_profiler/profiler/__init__.py
torch_tb_profiler/profiler/communication.py
torch_tb_profiler/profiler/data.py
torch_tb_profiler/profiler/event_parser.py
torch_tb_profiler/profiler/gpu_metrics_parser.py
torch_tb_profiler/profiler/kernel_parser.py
torch_tb_profiler/profiler/loader.py
torch_tb_profiler/profiler/memory_parser.py
torch_tb_profiler/profiler/module_op.py
torch_tb_profiler/profiler/node.py
torch_tb_profiler/profiler/op_agg.py
torch_tb_profiler/profiler/op_tree.py
torch_tb_profiler/profiler/overall_parser.py
torch_tb_profiler/profiler/range_utils.py
torch_tb_profiler/profiler/run_generator.py
torch_tb_profiler/profiler/tensor_core.py
torch_tb_profiler/profiler/tensor_cores_parser.py
torch_tb_profiler/profiler/trace.py
torch_tb_profiler/profiler/diffrun/__init__.py
torch_tb_profiler/profiler/diffrun/contract.py
torch_tb_profiler/profiler/diffrun/operator.py
torch_tb_profiler/profiler/diffrun/tree.py
torch_tb_profiler/static/index.html
torch_tb_profiler/static/index.js
torch_tb_profiler/static/trace_embedding.html
torch_tb_profiler/static/trace_script.js
torch_tb_profiler/static/trace_viewer_full.html
torch_tb_profiler_ascend-0.4.0.11.dist-info/LICENSE
torch_tb_profiler_ascend-0.4.0.11.dist-info/METADATA
torch_tb_profiler_ascend-0.4.0.11.dist-info/WHEEL
torch_tb_profiler_ascend-0.4.0.11.dist-info/entry_points.txt
torch_tb_profiler_ascend-0.4.0.11.dist-info/top_level.txt
torch_tb_profiler_ascend-0.4.0.11.dist-info/RECORD
